fxrelay_ui/__init__.py
fxrelay_ui/fxrelay_ui.css
fxrelay_ui-0.2.0.dist-info/METADATA
fxrelay_ui-0.2.0.dist-info/WHEEL
fxrelay_ui-0.2.0.dist-info/entry_points.txt
fxrelay_ui-0.2.0.dist-info/licenses/COPYING.WTFPL
fxrelay_ui-0.2.0.dist-info/RECORD
