Metadata-Version: 2.3
Name: fxrelay-ui
Version: 0.2.0
Summary: fxrelay-ui - manage your Firefox Relay mailboxes from the terminal
Project-URL: Homepage, https://gitlab.com/hydrargyrum/fxrelay-ui
License-Expression: WTFPL
License-File: COPYING.WTFPL
Keywords: email,firefox,privacy
Classifier: Development Status :: 4 - Beta
Classifier: Intended Audience :: Developers
Classifier: License :: Public Domain
Classifier: Programming Language :: Python :: 3
Classifier: Programming Language :: Python :: 3.7
Classifier: Programming Language :: Python :: 3.8
Classifier: Programming Language :: Python :: 3.9
Classifier: Programming Language :: Python :: 3.10
Classifier: Programming Language :: Python :: 3.11
Classifier: Topic :: Desktop Environment
Classifier: Topic :: Multimedia :: Graphics
Classifier: Topic :: Software Development :: Libraries :: Python Modules
Classifier: Topic :: Utilities
Requires-Python: >=3
Requires-Dist: httpx
Requires-Dist: textual
